{"is_source_file": false, "format": "", "description": "", "external_files": [], "external_methods": [], "published": [], "classes": [], "methods": [], "calls": [], "search-terms": ["HTML", "Database Viewer", "UI", "client-side", "JavaScript", "HTML structure", "CSS styles", "database list", "table view", "data rendering", "dynamic HTML", "AJAX fetch"], "state": 2, "file_id": 4, "knowledge_revision": 8, "git_revision": "1c47f68c11d5cb4ae2f1337f62f22fc4a391b66f", "hash": "ee63333a4841bf025439c755a74c9881", "format-version": 4, "code-base-name": "tic_tac_toe_database", "filename": "tic_tac_toe_database/db_visualizer/public/index.html", "revision_history": [{"8": "1c47f68c11d5cb4ae2f1337f62f22fc4a391b66f"}]}